klab_nifi_py/__init__.py
klab_nifi_py/commons.py
klab_nifi_py/contextualizer.py
klab_nifi_py/exception.py
klab_nifi_py/geometry.py
klab_nifi_py/logging.py
klab_nifi_py-0.0.2.dist-info/METADATA
klab_nifi_py-0.0.2.dist-info/WHEEL
klab_nifi_py-0.0.2.dist-info/top_level.txt
klab_nifi_py-0.0.2.dist-info/RECORD
