Metadata-Version: 2.4
Name: klab_nifi_py
Version: 0.0.2
Summary: Python Based Workflow to Interact with K.LAB Semantic Web, using Apache Nifi
Home-page: https://github.com/integratedmodelling/klab-nifi
Author: Arnab Moitra
Author-email: arnab.moitra@bc3research.org
Maintainer: Artificial Intelligence For Environment and Sustainability (ARIES) Team, Basque Centre for Climate Change (BC3)
Maintainer-email: support@integratedmodelling.org
Classifier: Programming Language :: Python :: 3
Classifier: License :: OSI Approved :: GNU Affero General Public License v3
Classifier: Operating System :: OS Independent
Requires-Python: >=3.10
Requires-Dist: shapely>=2.0.7
Dynamic: author
Dynamic: author-email
Dynamic: classifier
Dynamic: description
Dynamic: description-content-type
Dynamic: home-page
Dynamic: maintainer
Dynamic: maintainer-email
Dynamic: requires-dist
Dynamic: requires-python
Dynamic: summary
